sf_update.py
sf_object_tools-0.1.dist-info/METADATA
sf_object_tools-0.1.dist-info/WHEEL
sf_object_tools-0.1.dist-info/top_level.txt
sf_object_tools-0.1.dist-info/RECORD
