Metadata-Version: 2.1
Name: sf-object-tools
Version: 0.1
Summary: Open source project for processing object updates from salesforce
Home-page: https://github.com/openfibernet/sf_object_updates
Author: Dan Aronson
Author-email: dan@openfiber.net
License: UNKNOWN
Platform: UNKNOWN
Requires-Dist: boto3
